{
	"configurations" : 
	[
		{
			"directories" : 
			[
				{
					"build" : ".",
					"hasInstallRule" : true,
					"jsonFile" : "directory-.-Debug-7e9731b675c1cb032691.json",
					"minimumCMakeVersion" : 
					{
						"string" : "3.16"
					},
					"projectIndex" : 0,
					"source" : ".",
					"targetIndexes" : 
					[
						0,
						1,
						2
					]
				}
			],
			"name" : "Debug",
			"projects" : 
			[
				{
					"directoryIndexes" : 
					[
						0
					],
					"name" : "1-ListWidgetExample",
					"targetIndexes" : 
					[
						0,
						1,
						2
					]
				}
			],
			"targets" : 
			[
				{
					"directoryIndex" : 0,
					"id" : "1-ListWidgetExample::@6890427a1f51a3e7e1df",
					"jsonFile" : "target-1-ListWidgetExample-Debug-47dd4225dbdb63dea5bf.json",
					"name" : "1-ListWidgetExample",
					"projectIndex" : 0
				},
				{
					"directoryIndex" : 0,
					"id" : "1-ListWidgetExample_autogen::@6890427a1f51a3e7e1df",
					"jsonFile" : "target-1-ListWidgetExample_autogen-Debug-1ab221fd7922574edb1a.json",
					"name" : "1-ListWidgetExample_autogen",
					"projectIndex" : 0
				},
				{
					"directoryIndex" : 0,
					"id" : "1-ListWidgetExample_autogen_timestamp_deps::@6890427a1f51a3e7e1df",
					"jsonFile" : "target-1-ListWidgetExample_autogen_timestamp_deps-Debug-a6bfdd3e71f8449c98e0.json",
					"name" : "1-ListWidgetExample_autogen_timestamp_deps",
					"projectIndex" : 0
				}
			]
		}
	],
	"kind" : "codemodel",
	"paths" : 
	{
		"build" : "E:/Works/Qt Course/Qt Drag And Drop/build-1-ListWidgetExample-Desktop_Qt_6_3_1_MinGW_64_bit-Debug",
		"source" : "E:/Works/Qt Course/Qt Drag And Drop/1-ListWidgetExample"
	},
	"version" : 
	{
		"major" : 2,
		"minor" : 4
	}
}
